gplately/__init__.py
gplately/__main__.py
gplately/auxiliary.py
gplately/data.py
gplately/decorators.py
gplately/download.py
gplately/exceptions.py
gplately/geometry.py
gplately/gpml.py
gplately/grids.py
gplately/logging_config.yaml
gplately/oceans.py
gplately/parallel.py
gplately/plot.py
gplately/points.py
gplately/pygplates.py
gplately/reconstruction.py
gplately/spatial.py
gplately/tools.py
gplately/commands/__init__.py
gplately/commands/create_age_grids.py
gplately/commands/feature_filter.py
gplately/commands/list_models.py
gplately/commands/regrid.py
gplately/commands/reset_feature_type.py
gplately/lib/__init__.py
gplately/lib/icosahedron.py
gplately/lib/polyline.py
gplately/lib/quaternions.py
gplately/lib/reconstruct.py
gplately/lib/reconstruct_by_topologies.py
gplately/lib/rotation.py
gplately/mapping/__init__.py
gplately/mapping/cartopy_plot.py
gplately/mapping/plot_engine.py
gplately/mapping/pygmt_plot.py
gplately/ptt/__init__.py
gplately/ptt/cleanup_topologies.py
gplately/ptt/continent_contours.py
gplately/ptt/convert_xy_to_gplates.py
gplately/ptt/diagnose_rotations.py
gplately/ptt/fix_crossovers.py
gplately/ptt/gpmdb.py
gplately/ptt/remove_plate_rotations.py
gplately/ptt/resolve_topologies.py
gplately/ptt/ridge_spreading_rate.py
gplately/ptt/rotation_tools.py
gplately/ptt/separate_ridge_transform_segments.py
gplately/ptt/subduction_convergence.py
gplately/ptt/velocity_tools.py
gplately/ptt/utils/GPMLTools.py
gplately/ptt/utils/__init__.py
gplately/ptt/utils/call_system_command.py
gplately/ptt/utils/points_in_polygons.py
gplately/ptt/utils/points_spatial_tree.py
gplately/ptt/utils/proximity_query.py
gplately/ptt/utils/reconstruct_by_topologies.py
gplately/ptt/utils/subduction_teeth.py
gplately/utils/__init__.py
gplately/utils/check_pmm.py
gplately/utils/crustal_production.py
gplately/utils/dev_warning.py
gplately/utils/feature_utils.py
gplately/utils/io_utils.py
gplately/utils/log_utils.py
gplately/utils/plot_utils.py
gplately/utils/seafloor_grid_utils.py
gplately-2.0.0.dist-info/licenses/LICENSE
gplately-2.0.0.dist-info/METADATA
gplately-2.0.0.dist-info/WHEEL
gplately-2.0.0.dist-info/entry_points.txt
gplately-2.0.0.dist-info/top_level.txt
gplately-2.0.0.dist-info/RECORD
