Metadata-Version: 2.4
Name: gplately
Version: 2.0.0
Summary: Object-orientated Python interface to pyGPlates for plate tectonic reconstruction
Author-email: Ben Mather <ben.mather@sydney.edu.au>
License:                     GNU GENERAL PUBLIC LICENSE
Project-URL: Homepage, https://github.com/GPlates/gplately
Keywords: Tectonics,Earth
Classifier: License :: OSI Approved :: GNU General Public License v2 (GPLv2)
Classifier: Programming Language :: Python
Classifier: Programming Language :: Python :: 3
Classifier: Programming Language :: Python :: 3.9
Classifier: Programming Language :: Python :: 3.10
Classifier: Programming Language :: Python :: 3.11
Classifier: Programming Language :: Python :: 3.12
Classifier: Programming Language :: Python :: 3.13
Requires-Python: >=3.9
License-File: LICENSE
Requires-Dist: numpy>=1.16.0
Requires-Dist: scipy>=1.0.0
Requires-Dist: shapely
Requires-Dist: matplotlib
Requires-Dist: cartopy
Requires-Dist: pooch
Requires-Dist: tqdm
Requires-Dist: netcdf4
Requires-Dist: rasterio
Requires-Dist: geopandas
Requires-Dist: plate-model-manager>=1.3.0
Requires-Dist: pyyaml
Requires-Dist: pygmt
Requires-Dist: rioxarray
Requires-Dist: pygplates>=1.0.0
Provides-Extra: dev
Requires-Dist: black; extra == "dev"
Requires-Dist: bumpver; extra == "dev"
Requires-Dist: isort; extra == "dev"
Requires-Dist: pip-tools; extra == "dev"
Requires-Dist: pytest; extra == "dev"
Dynamic: license-file
